neural_insights/__init__.py
neural_insights/main.py
neural_insights/ni.py
neural_insights/version.py
neural_insights/bin/__init__.py
neural_insights/bin/neural_insights.py
neural_insights/components/__init__.py
neural_insights/components/diagnosis/__init__.py
neural_insights/components/diagnosis/diagnosis.py
neural_insights/components/diagnosis/factory.py
neural_insights/components/diagnosis/op_details.py
neural_insights/components/diagnosis/op_entry.py
neural_insights/components/diagnosis/weights_details.py
neural_insights/components/diagnosis/onnx_diagnosis/__init__.py
neural_insights/components/diagnosis/onnx_diagnosis/onnxrt_diagnosis.py
neural_insights/components/diagnosis/pytorch_diagnosis/__init__.py
neural_insights/components/diagnosis/pytorch_diagnosis/pytorch_diagnosis.py
neural_insights/components/diagnosis/tensorflow_diagnosis/__init__.py
neural_insights/components/diagnosis/tensorflow_diagnosis/tensorflow_diagnosis.py
neural_insights/components/graph/__init__.py
neural_insights/components/graph/attribute.py
neural_insights/components/graph/collapser.py
neural_insights/components/graph/edge.py
neural_insights/components/graph/graph.py
neural_insights/components/graph/graph_reader.py
neural_insights/components/graph/node.py
neural_insights/components/graph/reader/__init__.py
neural_insights/components/graph/reader/onnxrt_reader.py
neural_insights/components/graph/reader/pytorch_reader.py
neural_insights/components/graph/reader/tensorflow_reader.py
neural_insights/components/model/__init__.py
neural_insights/components/model/domain.py
neural_insights/components/model/model.py
neural_insights/components/model/model_type_getter.py
neural_insights/components/model/repository.py
neural_insights/components/model/shape.py
neural_insights/components/model/onnxrt/__init__.py
neural_insights/components/model/onnxrt/model.py
neural_insights/components/model/pytorch/__init__.py
neural_insights/components/model/pytorch/model.py
neural_insights-2.6.dist-info/LICENSE
neural_insights-2.6.dist-info/METADATA
neural_insights-2.6.dist-info/WHEEL
neural_insights-2.6.dist-info/entry_points.txt
neural_insights-2.6.dist-info/third-party-programs.txt
neural_insights-2.6.dist-info/top_level.txt
neural_insights-2.6.dist-info/RECORD
